equipparser/__init__.py
equipparser/_version.py
equipparser/dir_utils.py
equipparser/file_utils.py
equipparser/filing.py
equipparser/flatten_utils.py
equipparser/irsx_cli.py
equipparser/irsx_index_cli.py
equipparser/irsx_retrieve_cli.py
equipparser/keyerror_utils.py
equipparser/local_settings-example.py
equipparser/log_utils.py
equipparser/object_ids.py
equipparser/settings.py
equipparser/sked_dict_reader.py
equipparser/standardizer.py
equipparser/text_format_utils.py
equipparser/type_utils.py
equipparser/xmlrunner.py
equipparser/metadata/descriptions.csv
equipparser/metadata/groups.csv
equipparser/metadata/line_numbers.csv
equipparser/metadata/schedule_parts.csv
equipparser/metadata/variables.csv
equipparser-6.0.0.dist-info/licenses/LICENSE
equipparser-6.0.0.dist-info/METADATA
equipparser-6.0.0.dist-info/WHEEL
equipparser-6.0.0.dist-info/entry_points.txt
equipparser-6.0.0.dist-info/top_level.txt
equipparser-6.0.0.dist-info/RECORD
