Metadata-Version: 2.4
Name: equipparser
Version: 6.0.0
Summary: XML Parser
Home-page: https://github.com/vishalavalani/990-xml-reader
Author: Vishal Avalani
Author-email: vishal.avalani@gmail.com
License: MIT
Keywords: XML
Classifier: Development Status :: 3 - Alpha
Classifier: License :: OSI Approved :: MIT License
Classifier: Programming Language :: Python :: 2.7
Classifier: Programming Language :: Python :: 3.4
Classifier: Programming Language :: Python :: 3.5
Classifier: Programming Language :: Python :: 3.6
License-File: LICENSE
Requires-Dist: requests
Requires-Dist: xmltodict
Requires-Dist: unicodecsv
Dynamic: author
Dynamic: author-email
Dynamic: classifier
Dynamic: home-page
Dynamic: keywords
Dynamic: license
Dynamic: license-file
Dynamic: requires-dist
Dynamic: summary
